Metadata-Version: 1.1
Name: surface-area
Version: 0.0.1
Summary: finds surface area of 3D shapes
Home-page: UNKNOWN
Author: Elliott Weiss
Author-email: elliott.murray.weiss@gmail.com
License: UNKNOWN
Keywords: python,math,shapes,area
Platform: UNKNOWN
Classifier: Development Status :: 1 - Planning
Classifier: Intended Audience :: Developers
Classifier: Programming Language :: Python :: 3
Classifier: Operating System :: Unix
Classifier: Operating System :: MacOS :: MacOS X
Classifier: Operating System :: Microsoft :: Windows
